pyke_hooks/__init__.py
pyke_hooks/atlantis-yaml-generate.sh
pyke_hooks/atlantis_yaml_generate.py
pyke_hooks/tfsort.sh
pyke_hooks-0.1.2.dist-info/LICENSE
pyke_hooks-0.1.2.dist-info/METADATA
pyke_hooks-0.1.2.dist-info/WHEEL
pyke_hooks-0.1.2.dist-info/entry_points.txt
pyke_hooks-0.1.2.dist-info/RECORD
